numba_lapack/__init__.py
numba_lapack/__init__.pyi
numba_lapack/py.typed
numba_lapack/source.py
numba_lapack-0.1.2.dist-info/LICENSE
numba_lapack-0.1.2.dist-info/METADATA
numba_lapack-0.1.2.dist-info/WHEEL
numba_lapack-0.1.2.dist-info/top_level.txt
numba_lapack-0.1.2.dist-info/RECORD
