Metadata-Version: 2.2
Name: numba-lapack
Version: 0.1.2
Summary: UNSAFE Numba intrinsics for BLAS/LAPACK via SciPy C-API
Author: Mikołaj Tadeusz Żychowicz
License: Copyright (c) 2025, Mikołaj Tadeusz Żychowicz
Project-URL: Homepage, https://github.com/MTZ-dev/numba-lapack
Project-URL: Issues, https://github.com/MTZ-dev/numba-lapack/issues
Keywords: numba,blas,lapack,scipy,jit
Classifier: Programming Language :: Python :: 3
Classifier: Operating System :: OS Independent
Requires-Python: >=3.9
License-File: LICENSE
Requires-Dist: numpy>=1.24
Requires-Dist: scipy>=1.10
Requires-Dist: numba>=0.59
Requires-Dist: llvmlite>=0.42
